Metadata-Version: 1.2
Name: print-chat
Version: 0.4
Summary: Small print tool for implementing chat in the terminal
Home-page: https://github.com/IVIGOR13/print_chat
Author: IVIGOR13
Author-email: igor.i.v.a.13@gmail.com
License: MIT
Download-URL: https://github.com/IVIGOR13/print_chat/archive/0.4.tar.gz
Keywords: chat,terminal
Platform: UNKNOWN
Classifier: Development Status :: 4 - Beta
Classifier: Environment :: Console
Classifier: License :: OSI Approved :: MIT License
Classifier: Operating System :: OS Independent
Classifier: Programming Language :: Python
Classifier: Topic :: Terminals
Requires-Python: >=3
